zb_test_pkg/__init__.py
zb_test_pkg/mxmul.py
zb_test_pkg-0.1.0.dist-info/LICENSE
zb_test_pkg-0.1.0.dist-info/METADATA
zb_test_pkg-0.1.0.dist-info/WHEEL
zb_test_pkg-0.1.0.dist-info/top_level.txt
zb_test_pkg-0.1.0.dist-info/RECORD
