Metadata-Version: 2.1
Name: zb-test-pkg
Version: 0.1.0
Summary: An example for teaching how to publish a Python package
Home-page: https://github.com/pypa/sampleproject
Author: Bo Zhang
Author-email: tianniaozbl@163.com
License: UNKNOWN
Platform: UNKNOWN
Classifier: License :: OSI Approved :: MIT License
Classifier: Programming Language :: Python
Classifier: Intended Audience :: Developers
Classifier: Operating System :: OS Independent
License-File: LICENSE
